fastapi_toolkit/__init__.py
fastapi_toolkit/__main__.py
fastapi_toolkit/apis_generate/__init__.py
fastapi_toolkit/base/__init__.py
fastapi_toolkit/base/auth/__init__.py
fastapi_toolkit/base/auth/jwt/__init__.py
fastapi_toolkit/base/auth/jwt/auth.py
fastapi_toolkit/base/auth/key/__init__.py
fastapi_toolkit/base/auth/key/auth.py
fastapi_toolkit/base/endpoint.py
fastapi_toolkit/base/repo.py
fastapi_toolkit/base/router.py
fastapi_toolkit/configer.py
fastapi_toolkit/console.py
fastapi_toolkit/define/__init__.py
fastapi_toolkit/define/apis.py
fastapi_toolkit/define/config.py
fastapi_toolkit/define/mark.py
fastapi_toolkit/define/model.py
fastapi_toolkit/generate/__init__.py
fastapi_toolkit/generate/field_helper.py
fastapi_toolkit/generate/sql_mapping.py
fastapi_toolkit/generate/test/field_test.py
fastapi_toolkit/generate/utils.py
fastapi_toolkit/generate/view_plan.py
fastapi_toolkit/templates/api/main.py.j2
fastapi_toolkit/templates/auth/jwt/__init__.py.j2
fastapi_toolkit/templates/auth/jwt/models.py.j2
fastapi_toolkit/templates/auth/jwt/routes.py.j2
fastapi_toolkit/templates/auth/key/__init__.py.j2
fastapi_toolkit/templates/auth/key/routes.py.j2
fastapi_toolkit/templates/config.py.j2
fastapi_toolkit/templates/custom_types.py.j2
fastapi_toolkit/templates/db.py.jinja2
fastapi_toolkit/templates/dev.db.py.jinja2
fastapi_toolkit/templates/mock.py.j2
fastapi_toolkit/templates/models/main.py.jinja2
fastapi_toolkit/templates/repo/async/__init__.py.jinja2
fastapi_toolkit/templates/repo/async/main.py.jinja2
fastapi_toolkit/templates/repo/sync/__init__.py.jinja2
fastapi_toolkit/templates/repo/sync/main.py.jinja2
fastapi_toolkit/templates/routers/init.py.j2
fastapi_toolkit/templates/routers/main.py.j2
fastapi_toolkit/templates/schemas/main.py.jinja2
fastapi_toolkit/templates/setting.py.jinja2
fastapi_toolkit/templates/stub/__init__.py.jinja2
fastapi_toolkit/templates/stub/main.py.jinja2
fastapi_toolkit/templates/utils.j2
fastapi_toolkit/tests/test_configer.py
fastapi_toolkit_shawn587-0.2.3.16.dist-info/LICENSE
fastapi_toolkit_shawn587-0.2.3.16.dist-info/METADATA
fastapi_toolkit_shawn587-0.2.3.16.dist-info/WHEEL
fastapi_toolkit_shawn587-0.2.3.16.dist-info/entry_points.txt
fastapi_toolkit_shawn587-0.2.3.16.dist-info/RECORD
