Metadata-Version: 2.1
Name: fastapi_toolkit_shawn587
Version: 0.2.3.16
Summary: This toolkit can generate database CRUD operations based on defined metadata in one click, basic fastapi routing and mock data scripts.
Author: 0x587
Author-email: shawnsiu@outlook.com
Requires-Python: >=3.10,<4.0
Classifier: License :: OSI Approved :: MIT License
Classifier: Operating System :: OS Independent
Classifier: Programming Language :: Python :: 3
Classifier: Programming Language :: Python :: 3.10
Classifier: Programming Language :: Python :: 3.11
Classifier: Programming Language :: Python :: 3.12
Classifier: Programming Language :: Python :: 3.13
Requires-Dist: aiomysql (>=0.2.0,<0.3.0)
Requires-Dist: alembic (>=1.12.1,<2.0.0)
Requires-Dist: bcrypt (==4.0.1)
Requires-Dist: fastapi (==0.112.2)
Requires-Dist: fastapi-pagination (>=0.12.12,<0.13.0)
Requires-Dist: jinja2 (>=3.1.2,<4.0.0)
Requires-Dist: passlib[bcrypt] (>=1.7.4,<2.0.0)
Requires-Dist: pydantic (==2.8.2)
Requires-Dist: pydantic-settings (>=2.1.0,<3.0.0)
Requires-Dist: python-jose[cryptography] (>=3.3.0,<4.0.0)
Requires-Dist: python-multipart (>=0.0.6,<0.0.7)
Requires-Dist: pyyaml (>=6.0.1,<7.0.0)
Requires-Dist: sqlalchemy (>=2.0.23,<3.0.0)
Requires-Dist: typer[all] (>=0.9.0,<0.10.0)
Requires-Dist: uvicorn (>=0.24.0.post1,<0.25.0)
